odoo/addons/ssi_partner_creditor_debitor/README.rst
odoo/addons/ssi_partner_creditor_debitor/__init__.py
odoo/addons/ssi_partner_creditor_debitor/__manifest__.py
odoo/addons/ssi_partner_creditor_debitor/data/res_partner_category_data.xml
odoo/addons/ssi_partner_creditor_debitor/models/__init__.py
odoo/addons/ssi_partner_creditor_debitor/models/partner_creditor_debtor.py
odoo/addons/ssi_partner_creditor_debitor/models/res_partner.py
odoo/addons/ssi_partner_creditor_debitor/security/ir.model.access.csv
odoo/addons/ssi_partner_creditor_debitor/static/description/icon.png
odoo/addons/ssi_partner_creditor_debitor/views/res_partner_views.xml
odoo14_addon_ssi_partner_creditor_debitor-14.0.1.0.1.dev2.dist-info/METADATA
odoo14_addon_ssi_partner_creditor_debitor-14.0.1.0.1.dev2.dist-info/WHEEL
odoo14_addon_ssi_partner_creditor_debitor-14.0.1.0.1.dev2.dist-info/top_level.txt
odoo14_addon_ssi_partner_creditor_debitor-14.0.1.0.1.dev2.dist-info/RECORD
